gesture_blocks/__init__.py
gesture_blocks/core.py
gesture_blocks/led.py
gesture_blocks/otto.py
gesture_blocks/pose.py
gesture_blocks/sign.py
gesture_blocks/wonders.py
gesture_blocks-0.6.0.dist-info/METADATA
gesture_blocks-0.6.0.dist-info/WHEEL
gesture_blocks-0.6.0.dist-info/top_level.txt
gesture_blocks-0.6.0.dist-info/RECORD
